globus_mcp/__init__.py
globus_mcp/auth.py
globus_mcp/context.py
globus_mcp/server.py
globus_mcp/services/__init__.py
globus_mcp/services/compute/__init__.py
globus_mcp/services/compute/client.py
globus_mcp/services/compute/registry.py
globus_mcp/services/compute/schemas.py
globus_mcp/services/compute/tools.py
globus_mcp/services/transfer/__init__.py
globus_mcp/services/transfer/client.py
globus_mcp/services/transfer/registry.py
globus_mcp/services/transfer/schemas.py
globus_mcp/services/transfer/tools.py
globus_mcp-0.1.1.dist-info/METADATA
globus_mcp-0.1.1.dist-info/WHEEL
globus_mcp-0.1.1.dist-info/entry_points.txt
globus_mcp-0.1.1.dist-info/licenses/LICENSE
globus_mcp-0.1.1.dist-info/RECORD
