Metadata-Version: 2.4
Name: globus-mcp
Version: 0.1.1
Summary: Globus MCP server
Author-email: Globus <support@globus.org>
License-Expression: Apache-2.0
License-File: LICENSE
Keywords: globus,llm,mcp
Requires-Python: >=3.13
Requires-Dist: globus-compute-sdk<4.0.0,>=3.16.1
Requires-Dist: globus-sdk<4.0.0,>=3.65.0
Requires-Dist: mcp[cli]<2.0.0,>=1.16.0
